eda-orchestrator/rtl/alu16/cla4.v
`timescale 1ns / 1ps
// 4-bit Carry Lookahead Block
module cla4 (
    input  [3:0] a,
    input  [3:0] b,
    input        cin,
    output [3:0] sum,
    output       cout,
    output       P,   // group propagate
    output       G    // group generate
);
    wire [3:0] p, g;
    wire c1, c2, c3, c4;

    assign p = a ^ b;    // propagate
    assign g = a & b;    // generate

    assign c1 = g[0] | (p[0] & cin);
    assign c2 = g[1] | (p[1] & g[0]) | (p[1] & p[0] & cin);
    assign c3 = g[2] | (p[2] & g[1]) | (p[2] & p[1] & g[0]) |
                          (p[2] & p[1] & p[0] & cin);
    assign c4 = g[3] | (p[3] & g[2]) |
                          (p[3] & p[2] & g[1]) |
                          (p[3] & p[2] & p[1] & g[0]) |
                          (p[3] & p[2] & p[1] & p[0] & cin);

    assign sum[0] = p[0] ^ cin;
    assign sum[1] = p[1] ^ c1;
    assign sum[2] = p[2] ^ c2;
    assign sum[3] = p[3] ^ c3;

    assign cout = c4;

    // Group signals
    assign P = p[3] & p[2] & p[1] & p[0];
    assign G = g[3] | (p[3] & g[2]) |
                        (p[3] & p[2] & g[1]) |
                        (p[3] & p[2] & p[1] & g[0]);
endmodule

eda-orchestrator/rtl/alu16/cla16_addsub.v
`timescale 1ns / 1ps
// 16-bit Carry Lookahead Adder/Subtractor
module cla16_addsub (
    input  [15:0] a,
    input  [15:0] b,
    input         sub,      // 0: add, 1: subtract (a - b)
    output [15:0] sum,
    output        cout
);
    wire [15:0] b_xor;
    wire c0, c4, c8, c12, c16;
    wire [3:0] P, G;

    assign b_xor = b ^ {16{sub}}; // if sub=1 => invert b
    assign c0    = sub;           // add 1 for subtraction

    // 4-bit blocks
    cla4 u0 (.a(a[3:0]),   .b(b_xor[3:0]),   .cin(c0),
             .sum(sum[3:0]),   .cout(), .P(P[0]), .G(G[0]));

    assign c4 = G[0] | (P[0] & c0);

    cla4 u1 (.a(a[7:4]),   .b(b_xor[7:4]),   .cin(c4),
             .sum(sum[7:4]),   .cout(), .P(P[1]), .G(G[1]));

    assign c8 = G[1] | (P[1] & c4);

    cla4 u2 (.a(a[11:8]),  .b(b_xor[11:8]),  .cin(c8),
             .sum(sum[11:8]),  .cout(), .P(P[2]), .G(G[2]));

    assign c12 = G[2] | (P[2] & c8);

    cla4 u3 (.a(a[15:12]), .b(b_xor[15:12]), .cin(c12),
             .sum(sum[15:12]), .cout(), .P(P[3]), .G(G[3]));

    assign c16 = G[3] | (P[3] & c12);

    assign cout = c16;
endmodule

eda-orchestrator/rtl/alu16/alu.v
`timescale 1ns / 1ps

module alu (
    input  wire [15:0] a,
    input  wire [15:0] b,
    input  wire [3:0]  op,
    output reg  [15:0] y,
    output reg         carry,
    output reg         zero
);

    // ---------------------------------------
    // Internal signals
    // ---------------------------------------
    reg  [15:0] dummy_toggle;   // redundant logic for regression demo
    wire [15:0] addsub_sum;
    wire        addsub_cout;

    // ---------------------------------------
    // 16-bit CLA Adder/Subtractor
    // sub = 0 → ADD
    // sub = 1 → SUB
    // ---------------------------------------
    cla16_addsub u_addsub (
        .a    (a),
        .b    (b),
        .sub  (op[0]),
        .sum  (addsub_sum),
        .cout (addsub_cout)
    );

    // ---------------------------------------
    // ALU Operation Decode + Dummy Toggle
    // ---------------------------------------
    always @(*) begin
        carry = 1'b0;

        // 🔥 Redundant logic (does NOT affect outputs)
        // dummy_toggle = a ^ b;

        case (op)
            4'b0000: begin // ADD
                y     = addsub_sum;
                carry = addsub_cout;
            end

            4'b0001: begin // SUB
                y     = addsub_sum;
                carry = addsub_cout;
            end

            4'b0010: y = a & b;        // AND
            4'b0011: y = a | b;        // OR
            4'b0100: y = a ^ b;        // XOR
            4'b0101: y = ~a;           // NOT A
            4'b0110: y = a << 1;       // Shift left
            4'b0111: y = a >> 1;       // Shift right

            default: y = 16'h0000;
        endcase
    end

    // ---------------------------------------
    // Zero flag
    // ---------------------------------------
    always @(*) begin
        zero = (y == 16'h0000);
    end

endmodule

eda-orchestrator/rtl/alu16/alu_tb.v
`timescale 1ns / 1ps

module alu_tb;

    // -------------------------
    // DUT signals
    // -------------------------
    reg  [15:0] a;
    reg  [15:0] b;
    reg  [3:0]  op;
    wire [15:0] y;
    wire        carry;
    wire        zero;

    integer i;
    integer fh;

    // -------------------------
    // DUT : SINGLE TOP ALU
    // -------------------------
    alu dut (
        .a     (a),
        .b     (b),
        .op    (op),
        .y     (y),
        .carry (carry),
        .zero  (zero)
    );

    // -------------------------
    // VCD dump (MANDATORY)
    // -------------------------
    initial begin
        $dumpfile("alu.vcd");
        $dumpvars(0, alu_tb);
    end

    // -------------------------
    // Test + CSV logging
    // -------------------------
    initial begin
        fh = $fopen("alu_results.csv", "w");
        if (fh == 0) begin
            $finish;
        end

        // CSV header (FIXED FORMAT)
        $fwrite(fh, "cycle,a,b,op,y,carry,zero\n");

        // deterministic init
        a  = 16'd0;
        b  = 16'd0;
        op = 4'd0;

        #5;

        // Deterministic stimulus loop
        for (i = 0; i < 256; i = i + 1) begin
            a  = i;
            b  = 16'd255 - i;
            op = i % 8;   // valid ALU ops only

            #1;

            $fwrite(
                fh,
                "%0d,%0d,%0d,%0d,%0d,%0d,%0d\n",
                i, a, b, op, y, carry, zero
            );
        end

        $fclose(fh);
        #10;
        $finish;
    end

endmodule

eda-orchestrator/alu.vcd
$date
   Sat Dec 27 15:48:01 2025
$end

$version
  2023.2
  $dumpfile ("alu.vcd") 
$end

$timescale
  1ps
$end

$scope module alu_tb $end
$var reg 16 ! a [15:0] $end
$var reg 16 " b [15:0] $end
$var reg 4 # op [3:0] $end
$var wire 16 $ y [15:0] $end
$var wire 1 % carry $end
$var wire 1 & zero $end
$var integer 32 ' i [31:0] $end
$var integer 32 ( fh [31:0] $end
$scope module dut $end
$var wire 16 ) a [15:0] $end
$var wire 16 * b [15:0] $end
$var wire 4 + op [3:0] $end
$var reg 16 , y [15:0] $end
$var reg 1 - carry $end
$var reg 1 . zero $end
$var reg 16 / dummy_toggle [15:0] $end
$var wire 16 0 addsub_sum [15:0] $end
$var wire 1 1 addsub_cout $end
$scope module u_addsub $end
$var wire 16 ) a [15:0] $end
$var wire 16 * b [15:0] $end
$var wire 1 2 sub $end
$var wire 16 0 sum [15:0] $end
$var wire 1 1 cout $end
$var wire 16 3 b_xor [15:0] $end
$var wire 1 4 c0 $end
$var wire 1 5 c4 $end
$var wire 1 6 c8 $end
$var wire 1 7 c12 $end
$var wire 1 8 c16 $end
$var wire 4 9 P [3:0] $end
$var wire 4 : G [3:0] $end
$scope module u0 $end
$var wire 4 ; a [3:0] $end
$var wire 4 < b [3:0] $end
$var wire 1 4 cin $end
$var wire 4 = sum [3:0] $end
$var wire 1 > cout $end
$var wire 1 ? P $end
$var wire 1 @ G $end
$var wire 4 A p [3:0] $end
$var wire 4 B g [3:0] $end
$var wire 1 C c1 $end
$var wire 1 D c2 $end
$var wire 1 E c3 $end
$var wire 1 F c4 $end
$upscope $end
$scope module u1 $end
$var wire 4 G a [7:4] $end
$var wire 4 H b [7:4] $end
$var wire 1 5 cin $end
$var wire 4 I sum [7:4] $end
$var wire 1 J cout $end
$var wire 1 K P $end
$var wire 1 L G $end
$var wire 4 M p [3:0] $end
$var wire 4 N g [3:0] $end
$var wire 1 O c1 $end
$var wire 1 P c2 $end
$var wire 1 Q c3 $end
$var wire 1 R c4 $end
$upscope $end
$scope module u2 $end
$var wire 4 S a [11:8] $end
$var wire 4 T b [11:8] $end
$var wire 1 6 cin $end
$var wire 4 U sum [11:8] $end
$var wire 1 V cout $end
$var wire 1 W P $end
$var wire 1 X G $end
$var wire 4 Y p [3:0] $end
$var wire 4 Z g [3:0] $end
$var wire 1 [ c1 $end
$var wire 1 \ c2 $end
$var wire 1 ] c3 $end
$var wire 1 ^ c4 $end
$upscope $end
$scope module u3 $end
$var wire 4 _ a [15:12] $end
$var wire 4 ` b [15:12] $end
$var wire 1 7 cin $end
$var wire 4 a sum [15:12] $end
$var wire 1 b cout $end
$var wire 1 c P $end
$var wire 1 d G $end
$var wire 4 e p [3:0] $end
$var wire 4 f g [3:0] $end
$var wire 1 g c1 $end
$var wire 1 h c2 $end
$var wire 1 i c3 $end
$var wire 1 j c4 $end
$upscope $end
$upscope $end
$upscope $end
$upscope $end
$enddefinitions $end

#0
$dumpvars
b0 !
b0 "
b0 #
b0 $
0%
1&
bx '
b11111111111111111011000111100000 (
b0 )
b0 *
b0 +
b0 ,
0-
1.
bx /
b0 0
01
02
b0 3
04
05
06
07
08
b0 9
b0 :
b0 ;
b0 <
b0 =
0>
0?
0@
b0 A
b0 B
0C
0D
0E
0F
b0 G
b0 H
b0 I
0J
0K
0L
b0 M
b0 N
0O
0P
0Q
0R
b0 S
b0 T
b0 U
0V
0W
0X
b0 Y
b0 Z
0[
0\
0]
0^
b0 _
b0 `
b0 a
0b
0c
0d
b0 e
b0 f
0g
0h
0i
0j
$end

#5000
b11111111 "
b11111111 $
0&
b0 '
b11111111 *
b11111111 ,
0.
b11111111 0
b11111111 3
b11 9
b1111 <
b1111 =
1?
b1111 A
b1111 H
b1111 I
1K
b1111 M
b0 T
b0 `

#6000
b1 !
b11111110 "
b1 #
b1111111100000011 $
b1 '
b1 )
b11111110 *
b1 +
b1111111100000011 ,
b1111111100000011 0
12
b1111111100000001 3
14
05
b1100 9
b1 ;
b1 <
b11 =
0?
b0 A
b1 B
1C
b0 G
b0 H
b0 I
0K
b0 M
b0 S
b1111 T
b1111 U
1W
b1111 Y
b0 _
b1111 `
b1111 a
1c
b1111 e

#7000
b10 !
b11111101 "
b10 #
b0 $
1&
b10 '
b10 )
b11111101 *
b10 +
b0 ,
1.
b11111111 0
02
b11111101 3
04
b11 9
b10 ;
b1101 <
b1111 =
1?
b1111 A
b0 B
0C
b0 G
b1111 H
b1111 I
1K
b1111 M
b0 S
b0 T
b0 U
0W
b0 Y
b0 _
b0 `
b0 a
0c
b0 e

#8000
b11 !
b11111100 "
b11 #
b11111111 $
0&
b11 '
b11 )
b11111100 *
b11 +
b11111111 ,
0.
b1111111100000111 0
12
b1111111100000011 3
14
05
b1100 9
b11 ;
b11 <
b111 =
0?
b0 A
b11 B
1C
1D
b0 G
b0 H
b0 I
0K
b0 M
b0 S
b1111 T
b1111 U
1W
b1111 Y
b0 _
b1111 `
b1111 a
1c
b1111 e

#9000
b100 !
b11111011 "
b100 #
b100 '
b100 )
b11111011 *
b100 +
b11111111 0
02
b11111011 3
04
b11 9
b100 ;
b1011 <
b1111 =
1?
b1111 A
b0 B
0C
0D
b0 G
b1111 H
b1111 I
1K
b1111 M
b0 S
b0 T
b0 U
0W
b0 Y
b0 _
b0 `
b0 a
0c
b0 e

#10000
b101 !
b11111010 "
b101 #
b1111111111111010 $
b101 '
b101 )
b11111010 *
b101 +
b1111111111111010 ,
b1111111100001011 0
12
b1111111100000101 3
14
05
b1100 9
b101 ;
b101 <
b1011 =
0?
b0 A
b101 B
1C
1E
b0 G
b0 H
b0 I
0K
b0 M
b0 S
b1111 T
b1111 U
1W
b1111 Y
b0 _
b1111 `
b1111 a
1c
b1111 e

#11000
b110 !
b11111001 "
b110 #
b1100 $
b110 '
b110 )
b11111001 *
b110 +
b1100 ,
b11111111 0
02
b11111001 3
04
b11 9
b110 ;
b1001 <
b1111 =
1?
b1111 A
b0 B
0C
0E
b0 G
b1111 H
b1111 I
1K
b1111 M
b0 S
b0 T
b0 U
0W
b0 Y
b0 _
b0 `
b0 a
0c
b0 e

#12000
b111 !
b11111000 "
b111 #
b11 $
b111 '
b111 )
b11111000 *
b111 +
b11 ,
b1111111100001111 0
12
b1111111100000111 3
14
05
b1100 9
b111 ;
b111 <
0?
b0 A
b111 B
1C
1D
1E
b0 G
b0 H
b0 I
0K
b0 M
b0 S
b1111 T
b1111 U
1W
b1111 Y
b0 _
b1111 `
b1111 a
1c
b1111 e

#13000
b1000 !
b11110111 "
b0 #
b11111111 $
b1000 '
b1000 )
b11110111 *
b0 +
b11111111 ,
b11111111 0
02
b11110111 3
04
b11 9
b1000 ;
b111 <
1?
b1111 A
b0 B
0C
0D
0E
b0 G
b1111 H
b1111 I
1K
b1111 M
b0 S
b0 T
b0 U
0W
b0 Y
b0 _
b0 `
b0 a
0c
b0 e

#14000
b1001 !
b11110110 "
b1 #
b1111111100010011 $
b1001 '
b1001 )
b11110110 *
b1 +
b1111111100010011 ,
b1111111100010011 0
12
b1111111100001001 3
14
15
b1100 9
b1 :
b1001 ;
b1001 <
b11 =
1>
0?
1@
b0 A
b1001 B
1C
1F
b0 G
b0 H
b1 I
0K
b0 M
b0 S
b1111 T
b1111 U
1W
b1111 Y
b0 _
b1111 `
b1111 a
1c
b1111 e

#15000
b1010 !
b11110101 "
b10 #
b0 $
1&
b1010 '
b1010 )
b11110101 *
b10 +
b0 ,
1.
b11111111 0
02
b11110101 3
04
05
b11 9
b0 :
b1010 ;
b101 <
b1111 =
0>
1?
0@
b1111 A
b0 B
0C
0F
b0 G
b1111 H
b1111 I
0J
1K
b1111 M
0O
0P
0Q
0R
b0 S
b0 T
b0 U
0W
b0 Y
b0 _
b0 `
b0 a
0c
b0 e

#16000
b1011 !
b11110100 "
b11 #
b11111111 $
0&
b1011 '
b1011 )
b11110100 *
b11 +
b11111111 ,
0.
b1111111100010111 0
12
b1111111100001011 3
14
15
b1100 9
b1 :
b1011 ;
b1011 <
b111 =
1>
0?
1@
b0 A
b1011 B
1C
1D
1F
b0 G
b0 H
b1 I
0K
b0 M
b0 S
b1111 T
b1111 U
1W
b1111 Y
b0 _
b1111 `
b1111 a
1c
b1111 e

#17000
b1100 !
b11110011 "
b100 #
b1100 '
b1100 )
b11110011 *
b100 +
b11111111 0
02
b11110011 3
04
05
b11 9
b0 :
b1100 ;
b11 <
b1111 =
0>
1?
0@
b1111 A
b0 B
0C
0D
0F
b0 G
b1111 H
b1111 I
0J
1K
b1111 M
0O
0P
0Q
0R
b0 S
b0 T
b0 U
0W
b0 Y
b0 _
b0 `
b0 a
0c
b0 e

#18000
b1101 !
b11110010 "
b101 #
b1111111111110010 $
b1101 '
b1101 )
b11110010 *
b101 +
b1111111111110010 ,
b1111111100011011 0
12
b1111111100001101 3
14
15
b1100 9
b1 :
b1101 ;
b1101 <
b1011 =
1>
0?
1@
b0 A
b1101 B
1C
1E
1F
b0 G
b0 H
b1 I
0K
b0 M
b0 S
b1111 T
b1111 U
1W
b1111 Y
b0 _
b1111 `
b1111 a
1c
b1111 e

#19000
b1110 !
b11110001 "
b110 #
b11100 $
b1110 '
b1110 )
b11110001 *
b110 +
b11100 ,
b11111111 0
02
b11110001 3
04
05
b11 9
b0 :
b1110 ;
b1 <
b1111 =
0>
1?
0@
b1111 A
b0 B
0C
0E
0F
b0 G
b1111 H
b1111 I
0J
1K
b1111 M
0O
0P
0Q
0R
b0 S
b0 T
b0 U
0W
b0 Y
b0 _
b0 `
b0 a
0c
b0 e

#20000
b1111 !
b11110000 "
b111 #
b111 $
b1111 '
b1111 )
b11110000 *
b111 +
b111 ,
b1111111100011111 0
12
b1111111100001111 3
14
15
b1100 9
b1 :
b1111 ;
b1111 <
1>
0?
1@
b0 A
b1111 B
1C
1D
1E
1F
b0 G
b0 H
b1 I
0K
b0 M
b0 S
b1111 T
b1111 U
1W
b1111 Y
b0 _
b1111 `
b1111 a
1c
b1111 e

#21000
b10000 !
b11101111 "
b0 #
b11111111 $
b10000 '
b10000 )
b11101111 *
b0 +
b11111111 ,
b11111111 0
02
b11101111 3
04
05
b11 9
b0 :
b0 ;
b1111 <
0>
1?
0@
b1111 A
b0 B
0C
0D
0E
0F
b1 G
b1110 H
b1111 I
0J
1K
b1111 M
0O
0P
0Q
0R
b0 S
b0 T
b0 U
0W
b0 Y
b0 _
b0 `
b0 a
0c
b0 e

#22000
b10001 !
b11101110 "
b1 #
b1111111100100011 $
b10001 '
b10001 )
b11101110 *
b1 +
b1111111100100011 ,
b1111111100100011 0
12
b1111111100010001 3
14
05
b1100 9
b1 ;
b1 <
b11 =
0?
b0 A
b1 B
1C
b1 G
b1 H
b10 I
0K
b0 M
b1 N
1O
b0 S
b1111 T
b1111 U
1W
b1111 Y
b0 _
b1111 `
b1111 a
1c
b1111 e

#23000
b10010 !
b11101101 "
b10 #
b0 $
1&
b10010 '
b10010 )
b11101101 *
b10 +
b0 ,
1.
b11111111 0
02
b11101101 3
04
b11 9
b10 ;
b1101 <
b1111 =
1?
b1111 A
b0 B
0C
b1 G
b1110 H
b1111 I
1K
b1111 M
b0 N
0O
b0 S
b0 T
b0 U
0W
b0 Y
b0 _
b0 `
b0 a
0c
b0 e

#24000
b10011 !
b11101100 "
b11 #
b11111111 $
0&
b10011 '
b10011 )
b11101100 *
b11 +
b11111111 ,
0.
b1111111100100111 0
12
b1111111100010011 3
14
05
b1100 9
b11 ;
b11 <
b111 =
0?
b0 A
b11 B
1C
1D
b1 G
b1 H
b10 I
0K
b0 M
b1 N
1O
b0 S
b1111 T
b1111 U
1W
b1111 Y
b0 _
b1111 `
b1111 a
1c
b1111 e

#25000
b10100 !
b11101011 "
b100 #
b10100 '
b10100 )
b11101011 *
b100 +
b11111111 0
02
b11101011 3
04
b11 9
b100 ;
b1011 <
b1111 =
1?
b1111 A
b0 B
0C
0D
b1 G
b1110 H
b1111 I
1K
b1111 M
b0 N
0O
b0 S
b0 T
b0 U
0W
b0 Y
b0 _
b0 `
b0 a
0c
b0 e

#26000
b10101 !
b11101010 "
b101 #
b1111111111101010 $
b10101 '
b10101 )
b11101010 *
b101 +
b1111111111101010 ,
b1111111100101011 0
12
b1111111100010101 3
14
05
b1100 9
b101 ;
b101 <
b1011 =
0?
b0 A
b101 B
1C
1E
b1 G
b1 H
b10 I
0K
b0 M
b1 N
1O
b0 S
b1111 T
b1111 U
1W
b1111 Y
b0 _
b1111 `
b1111 a
1c
b1111 e

#27000
b10110 !
b11101001 "
b110 #
b101100 $
b10110 '
b10110 )
b11101001 *
b110 +
b101100 ,
b11111111 0
02
b11101001 3
04
b11 9
b110 ;
b1001 <
b1111 =
1?
b1111 A
b0 B
0C
0E
b1 G
b1110 H
b1111 I
1K
b1111 M
b0 N
0O
b0 S
b0 T
b0 U
0W
b0 Y
b0 _
b0 `
b0 a
0c
b0 e

#28000
b10111 !
b11101000 "
b111 #
b1011 $
b10111 '
b10111 )
b11101000 *
b111 +
b1011 ,
b1111111100101111 0
12
b1111111100010111 3
14
05
b1100 9
b111 ;
b111 <
0?
b0 A
b111 B
1C
1D
1E
b1 G
b1 H
b10 I
0K
b0 M
b1 N
1O
b0 S
b1111 T
b1111 U
1W
b1111 Y
b0 _
b1111 `
b1111 a
1c
b1111 e

#29000
b11000 !
b11100111 "
b0 #
b11111111 $
b11000 '
b11000 )
b11100111 *
b0 +
b11111111 ,
b11111111 0
02
b11100111 3
04
b11 9
b1000 ;
b111 <
1?
b1111 A
b0 B
0C
0D
0E
b1 G
b1110 H
b1111 I
1K
b1111 M
b0 N
0O
b0 S
b0 T
b0 U
0W
b0 Y
b0 _
b0 `
b0 a
0c
b0 e

#30000
b11001 !
b11100110 "
b1 #
b1111111100110011 $
b11001 '
b11001 )
b11100110 *
b1 +
b1111111100110011 ,
b1111111100110011 0
12
b1111111100011001 3
14
15
b1100 9
b1 :
b1001 ;
b1001 <
b11 =
1>
0?
1@
b0 A
b1001 B
1C
1F
b1 G
b1 H
b11 I
0K
b0 M
b1 N
1O
b0 S
b1111 T
b1111 U
1W
b1111 Y
b0 _
b1111 `
b1111 a
1c
b1111 e

#31000
b11010 !
b11100101 "
b10 #
b0 $
1&
b11010 '
b11010 )
b11100101 *
b10 +
b0 ,
1.
b11111111 0
02
b11100101 3
04
05
b11 9
b0 :
b1010 ;
b101 <
b1111 =
0>
1?
0@
b1111 A
b0 B
0C
0F
b1 G
b1110 H
b1111 I
0J
1K
b1111 M
b0 N
0O
0P
0Q
0R
b0 S
b0 T
b0 U
0W
b0 Y
b0 _
b0 `
b0 a
0c
b0 e

#32000
b11011 !
b11100100 "
b11 #
b11111111 $
0&
b11011 '
b11011 )
b11100100 *
b11 +
b11111111 ,
0.
b1111111100110111 0
12
b1111111100011011 3
14
15
b1100 9
b1 :
b1011 ;
b1011 <
b111 =
1>
0?
1@
b0 A
b1011 B
1C
1D
1F
b1 G
b1 H
b11 I
0K
b0 M
b1 N
1O
b0 S
b1111 T
b1111 U
1W
b1111 Y
b0 _
b1111 `
b1111 a
1c
b1111 e

#33000
b11100 !
b11100011 "
b100 #
b11100 '
b11100 )
b11100011 *
b100 +
b11111111 0
02
b11100011 3
04
05
b11 9
b0 :
b1100 ;
b11 <
b1111 =
0>
1?
0@
b1111 A
b0 B
0C
0D
0F
b1 G
b1110 H
b1111 I
0J
1K
b1111 M
b0 N
0O
0P
0Q
0R
b0 S
b0 T
b0 U
0W
b0 Y
b0 _
b0 `
b0 a
0c
b0 e

#34000
b11101 !
b11100010 "
b101 #
b1111111111100010 $
b11101 '
b11101 )
b11100010 *
b101 +
b1111111111100010 ,
b1111111100111011 0
12
b1111111100011101 3
14
15
b1100 9
b1 :
b1101 ;
b1101 <
b1011 =
1>
0?
1@
b0 A
b1101 B
1C
1E
1F
b1 G
b1 H
b11 I
0K
b0 M
b1 N
1O
b0 S
b1111 T
b1111 U
1W
b1111 Y
b0 _
b1111 `
b1111 a
1c
b1111 e

#35000
b11110 !
b11100001 "
b110 #
b111100 $
b11110 '
b11110 )
b11100001 *
b110 +
b111100 ,
b11111111 0
02
b11100001 3
04
05
b11 9
b0 :
b1110 ;
b1 <
b1111 =
0>
1?
0@
b1111 A
b0 B
0C
0E
0F
b1 G
b1110 H
b1111 I
0J
1K
b1111 M
b0 N
0O
0P
0Q
0R
b0 S
b0 T
b0 U
0W
b0 Y
b0 _
b0 `
b0 a
0c
b0 e

#36000
b11111 !
b11100000 "
b111 #
b1111 $
b11111 '
b11111 )
b11100000 *
b111 +
b1111 ,
b1111111100111111 0
12
b1111111100011111 3
14
15
b1100 9
b1 :
b1111 ;
b1111 <
1>
0?
1@
b0 A
b1111 B
1C
1D
1E
1F
b1 G
b1 H
b11 I
0K
b0 M
b1 N
1O
b0 S
b1111 T
b1111 U
1W
b1111 Y
b0 _
b1111 `
b1111 a
1c
b1111 e

#37000
b100000 !
b11011111 "
b0 #
b11111111 $
b100000 '
b100000 )
b11011111 *
b0 +
b11111111 ,
b11111111 0
02
b11011111 3
04
05
b11 9
b0 :
b0 ;
b1111 <
0>
1?
0@
b1111 A
b0 B
0C
0D
0E
0F
b10 G
b1101 H
b1111 I
0J
1K
b1111 M
b0 N
0O
0P
0Q
0R
b0 S
b0 T
b0 U
0W
b0 Y
b0 _
b0 `
b0 a
0c
b0 e

#38000
b100001 !
b11011110 "
b1 #
b1111111101000011 $
b100001 '
b100001 )
b11011110 *
b1 +
b1111111101000011 ,
b1111111101000011 0
12
b1111111100100001 3
14
05
b1100 9
b1 ;
b1 <
b11 =
0?
b0 A
b1 B
1C
b10 G
b10 H
b100 I
0K
b0 M
b10 N
1P
b0 S
b1111 T
b1111 U
1W
b1111 Y
b0 _
b1111 `
b1111 a
1c
b1111 e

#39000
b100010 !
b11011101 "
b10 #
b0 $
1&
b100010 '
b100010 )
b11011101 *
b10 +
b0 ,
1.
b11111111 0
02
b11011101 3
04
b11 9
b10 ;
b1101 <
b1111 =
1?
b1111 A
b0 B
0C
b10 G
b1101 H
b1111 I
1K
b1111 M
b0 N
0P
b0 S
b0 T
b0 U
0W
b0 Y
b0 _
b0 `
b0 a
0c
b0 e

#40000
b100011 !
b11011100 "
b11 #
b11111111 $
0&
b100011 '
b100011 )
b11011100 *
b11 +
b11111111 ,
0.
b1111111101000111 0
12
b1111111100100011 3
14
05
b1100 9
b11 ;
b11 <
b111 =
0?
b0 A
b11 B
1C
1D
b10 G
b10 H
b100 I
0K
b0 M
b10 N
1P
b0 S
b1111 T
b1111 U
1W
b1111 Y
b0 _
b1111 `
b1111 a
1c
b1111 e

#41000
b100100 !
b11011011 "
b100 #
b100100 '
b100100 )
b11011011 *
b100 +
b11111111 0
02
b11011011 3
04
b11 9
b100 ;
b1011 <
b1111 =
1?
b1111 A
b0 B
0C
0D
b10 G
b1101 H
b1111 I
1K
b1111 M
b0 N
0P
b0 S
b0 T
b0 U
0W
b0 Y
b0 _
b0 `
b0 a
0c
b0 e

#42000
b100101 !
b11011010 "
b101 #
b1111111111011010 $
b100101 '
b100101 )
b11011010 *
b101 +
b1111111111011010 ,
b1111111101001011 0
12
b1111111100100101 3
14
05
b1100 9
b101 ;
b101 <
b1011 =
0?
b0 A
b101 B
1C
1E
b10 G
b10 H
b100 I
0K
b0 M
b10 N
1P
b0 S
b1111 T
b1111 U
1W
b1111 Y
b0 _
b1111 `
b1111 a
1c
b1111 e

#43000
b100110 !
b11011001 "
b110 #
b1001100 $
b100110 '
b100110 )
b11011001 *
b110 +
b1001100 ,
b11111111 0
02
b11011001 3
04
b11 9
b110 ;
b1001 <
b1111 =
1?
b1111 A
b0 B
0C
0E
b10 G
b1101 H
b1111 I
1K
b1111 M
b0 N
0P
b0 S
b0 T
b0 U
0W
b0 Y
b0 _
b0 `
b0 a
0c
b0 e

#44000
b100111 !
b11011000 "
b111 #
b10011 $
b100111 '
b100111 )
b11011000 *
b111 +
b10011 ,
b1111111101001111 0
12
b1111111100100111 3
14
05
b1100 9
b111 ;
b111 <
0?
b0 A
b111 B
1C
1D
1E
b10 G
b10 H
b100 I
0K
b0 M
b10 N
1P
b0 S
b1111 T
b1111 U
1W
b1111 Y
b0 _
b1111 `
b1111 a
1c
b1111 e

#45000
b101000 !
b11010111 "
b0 #
b11111111 $
b101000 '
b101000 )
b11010111 *
b0 +
b11111111 ,
b11111111 0
02
b11010111 3
04
b11 9
b1000 ;
b111 <
1?
b1111 A
b0 B
0C
0D
0E
b10 G
b1101 H
b1111 I
1K
b1111 M
b0 N
0P
b0 S
b0 T
b0 U
0W
b0 Y
b0 _
b0 `
b0 a
0c
b0 e

#46000
b101001 !
b11010110 "
b1 #
b1111111101010011 $
b101001 '
b101001 )
b11010110 *
b1 +
b1111111101010011 ,
b1111111101010011 0
12
b1111111100101001 3
14
15
b1100 9
b1 :
b1001 ;
b1001 <
b11 =
1>
0?
1@
b0 A
b1001 B
1C
1F
b10 G
b10 H
b101 I
0K
b0 M
b10 N
1P
b0 S
b1111 T
b1111 U
1W
b1111 Y
b0 _
b1111 `
b1111 a
1c
b1111 e

#47000
b101010 !
b11010101 "
b10 #
b0 $
1&
b101010 '
b101010 )
b11010101 *
b10 +
b0 ,
1.
b11111111 0
02
b11010101 3
04
05
b11 9
b0 :
b1010 ;
b101 <
b1111 =
0>
1?
0@
b1111 A
b0 B
0C
0F
b10 G
b1101 H
b1111 I
0J
1K
b1111 M
b0 N
0O
0P
0Q
0R
b0 S
b0 T
b0 U
0W
b0 Y
b0 _
b0 `
b0 a
0c
b0 e

#48000
b101011 !
b11010100 "
b11 #
b11111111 $
0&
b101011 '
b101011 )
b11010100 *
b11 +
b11111111 ,
0.
b1111111101010111 0
12
b1111111100101011 3
14
15
b1100 9
b1 :
b1011 ;
b1011 <
b111 =
1>
0?
1@
b0 A
b1011 B
1C
1D
1F
b10 G
b10 H
b101 I
0K
b0 M
b10 N
1P
b0 S
b1111 T
b1111 U
1W
b1111 Y
b0 _
b1111 `
b1111 a
1c
b1111 e

#49000
b101100 !
b11010011 "
b100 #
b101100 '
b101100 )
b11010011 *
b100 +
b11111111 0
02
b11010011 3
04
05
b11 9
b0 :
b1100 ;
b11 <
b1111 =
0>
1?
0@
b1111 A
b0 B
0C
0D
0F
b10 G
b1101 H
b1111 I
0J
1K
b1111 M
b0 N
0O
0P
0Q
0R
b0 S
b0 T
b0 U
0W
b0 Y
b0 _
b0 `
b0 a
0c
b0 e

#50000
b101101 !
b11010010 "
b101 #
b1111111111010010 $
b101101 '
b101101 )
b11010010 *
b101 +
b1111111111010010 ,
b1111111101011011 0
12
b1111111100101101 3
14
15
b1100 9
b1 :
b1101 ;
b1101 <
b1011 =
1>
0?
1@
b0 A
b1101 B
1C
1E
1F
b10 G
b10 H
b101 I
0K
b0 M
b10 N
1P
b0 S
b1111 T
b1111 U
1W
b1111 Y
b0 _
b1111 `
b1111 a
1c
b1111 e

#51000
b101110 !
b11010001 "
b110 #
b1011100 $
b101110 '
b101110 )
b11010001 *
b110 +
b1011100 ,
b11111111 0
02
b11010001 3
04
05
b11 9
b0 :
b1110 ;
b1 <
b1111 =
0>
1?
0@
b1111 A
b0 B
0C
0E
0F
b10 G
b1101 H
b1111 I
0J
1K
b1111 M
b0 N
0O
0P
0Q
0R
b0 S
b0 T
b0 U
0W
b0 Y
b0 _
b0 `
b0 a
0c
b0 e

#52000
b101111 !
b11010000 "
b111 #
b10111 $
b101111 '
b101111 )
b11010000 *
b111 +
b10111 ,
b1111111101011111 0
12
b1111111100101111 3
14
15
b1100 9
b1 :
b1111 ;
b1111 <
1>
0?
1@
b0 A
b1111 B
1C
1D
1E
1F
b10 G
b10 H
b101 I
0K
b0 M
b10 N
1P
b0 S
b1111 T
b1111 U
1W
b1111 Y
b0 _
b1111 `
b1111 a
1c
b1111 e

#53000
b110000 !
b11001111 "
b0 #
b11111111 $
b110000 '
b110000 )
b11001111 *
b0 +
b11111111 ,
b11111111 0
02
b11001111 3
04
05
b11 9
b0 :
b0 ;
b1111 <
0>
1?
0@
b1111 A
b0 B
0C
0D
0E
0F
b11 G
b1100 H
b1111 I
0J
1K
b1111 M
b0 N
0O
0P
0Q
0R
b0 S
b0 T
b0 U
0W
b0 Y
b0 _
b0 `
b0 a
0c
b0 e

